{
    "objects": [
        {
            "type": "staticObject",
            "model": "rock",
            "path": "public/worlds/rock.glb",
            "position": { "x": 5, "y": 0, "z": -10 },
            "rotation": { "x": 0, "y": 0.5, "z": 0 },
            "scale": { "x": 1, "y": 1, "z": 1 }
        },
        {
            "type": "staticObject",
            "model": "tree",
            "path": "public/worlds/tree.glb",
            "position": { "x": -8, "y": 0, "z": 4 },
            "rotation": { "x": 0, "y": 0, "z": 0 },
            "scale": { "x": 1.2, "y": 1.2, "z": 1.2 }
        }
    ]
}
